multiel_spectra/__init__.py
multiel_spectra/gpu_spectra.py
multiel_spectra/install_skbeam.py
multiel_spectra/install_spekpy.py
multiel_spectra/multiel_spectra.py
multiel_spectra/xrf_utils.py
multiel_spectra-0.1.0.0.5.dist-info/LICENSE
multiel_spectra-0.1.0.0.5.dist-info/METADATA
multiel_spectra-0.1.0.0.5.dist-info/WHEEL
multiel_spectra-0.1.0.0.5.dist-info/dependency_links.txt
multiel_spectra-0.1.0.0.5.dist-info/top_level.txt
multiel_spectra-0.1.0.0.5.dist-info/RECORD
