Metadata-Version: 2.1
Name: multiel_spectra
Version: 0.1.0.0.5
Summary: Multi-Element Fluorescence Xray Spectra Generator
Home-page: https://baltig.infn.it/fgarciaa/multiel_spectra
Author: Fernando Garcia-Avello 
Author-email: fgarciaa@fi.infn.it
Project-URL: Documentation, https://baltig.infn.it/fgarciaa/multiel_spectra
Project-URL: Bug Reports, https://baltig.infn.it/fgarciaa/multiel_spectra
Project-URL: Source Code, https://baltig.infn.it/fgarciaa/multiel_spectra
Keywords: xray,fluorescence,pypi,package
Classifier: Development Status :: 4 - Beta
Classifier: Intended Audience :: Developers
Classifier: Topic :: Software Development :: Build Tools
Classifier: Programming Language :: Python :: 3
Classifier: Programming Language :: Python :: 3.6
Classifier: Programming Language :: Python :: 3.7
Classifier: Programming Language :: Python :: 3.8
Classifier: Programming Language :: Python :: 3.9
Classifier: Programming Language :: Python :: 3 :: Only
Classifier: License :: OSI Approved :: MIT License
Classifier: Operating System :: OS Independent
Requires-Python: >=3.6
License-File: LICENSE
Requires-Dist: xraylarch >=0.9.68
Requires-Dist: scipy
Requires-Dist: pandas
Requires-Dist: numpy
Requires-Dist: matplotlib
Requires-Dist: bokeh
Provides-Extra: dev
Requires-Dist: check-manifest ; extra == 'dev'
Provides-Extra: torch
Requires-Dist: torch ; extra == 'torch'
